{"nodes": [{"id": "stock", "label": "stock.py", "file_type": "code", "source_file": "backend/src/models/stock.py", "source_location": "L1"}, {"id": "stock_chartdatapoint", "label": "ChartDataPoint", "file_type": "code", "source_file": "backend/src/models/stock.py", "source_location": "L8"}, {"id": "basemodel", "label": "BaseModel", "file_type": "code", "source_file": "", "source_location": ""}, {"id": "stock_stockstats", "label": "StockStats", "file_type": "code", "source_file": "backend/src/models/stock.py", "source_location": "L20"}, {"id": "stock_companydetail", "label": "CompanyDetail", "file_type": "code", "source_file": "backend/src/models/stock.py", "source_location": "L27"}, {"id": "stock_topmover", "label": "TopMover", "file_type": "code", "source_file": "backend/src/models/stock.py", "source_location": "L51"}, {"id": "stock_rationale_1", "label": "Stock-related Pydantic models", "file_type": "rationale", "source_file": "backend/src/models/stock.py", "source_location": "L1"}, {"id": "stock_rationale_9", "label": "Single OHLCV data point for stock chart", "file_type": "rationale", "source_file": "backend/src/models/stock.py", "source_location": "L9"}, {"id": "stock_rationale_21", "label": "Additional stock statistics", "file_type": "rationale", "source_file": "backend/src/models/stock.py", "source_location": "L21"}, {"id": "stock_rationale_28", "label": "Detailed company/stock information", "file_type": "rationale", "source_file": "backend/src/models/stock.py", "source_location": "L28"}, {"id": "stock_rationale_52", "label": "Top price mover stock information", "file_type": "rationale", "source_file": "backend/src/models/stock.py", "source_location": "L52"}], "edges": [{"source": "stock", "target": "pydantic", "relation": "imports_from", "confidence": "EXTRACTED", "source_file": "backend/src/models/stock.py", "source_location": "L4", "weight": 1.0}, {"source": "stock", "target": "typing", "relation": "imports_from", "confidence": "EXTRACTED", "source_file": "backend/src/models/stock.py", "source_location": "L5", "weight": 1.0}, {"source": "stock", "target": "stock_chartdatapoint", "relation": "contains", "confidence": "EXTRACTED", "source_file": "backend/src/models/stock.py", "source_location": "L8", "weight": 1.0}, {"source": "stock_chartdatapoint", "target": "basemodel", "relation": "inherits", "confidence": "EXTRACTED", "source_file": "backend/src/models/stock.py", "source_location": "L8", "weight": 1.0}, {"source": "stock", "target": "stock_stockstats", "relation": "contains", "confidence": "EXTRACTED", "source_file": "backend/src/models/stock.py", "source_location": "L20", "weight": 1.0}, {"source": "stock_stockstats", "target": "basemodel", "relation": "inherits", "confidence": "EXTRACTED", "source_file": "backend/src/models/stock.py", "source_location": "L20", "weight": 1.0}, {"source": "stock", "target": "stock_companydetail", "relation": "contains", "confidence": "EXTRACTED", "source_file": "backend/src/models/stock.py", "source_location": "L27", "weight": 1.0}, {"source": "stock_companydetail", "target": "basemodel", "relation": "inherits", "confidence": "EXTRACTED", "source_file": "backend/src/models/stock.py", "source_location": "L27", "weight": 1.0}, {"source": "stock", "target": "stock_topmover", "relation": "contains", "confidence": "EXTRACTED", "source_file": "backend/src/models/stock.py", "source_location": "L51", "weight": 1.0}, {"source": "stock_topmover", "target": "basemodel", "relation": "inherits", "confidence": "EXTRACTED", "source_file": "backend/src/models/stock.py", "source_location": "L51", "weight": 1.0}, {"source": "stock_rationale_1", "target": "stock", "relation": "rationale_for", "confidence": "EXTRACTED", "source_file": "backend/src/models/stock.py", "source_location": "L1", "weight": 1.0}, {"source": "stock_rationale_9", "target": "stock_chartdatapoint", "relation": "rationale_for", "confidence": "EXTRACTED", "source_file": "backend/src/models/stock.py", "source_location": "L9", "weight": 1.0}, {"source": "stock_rationale_21", "target": "stock_stockstats", "relation": "rationale_for", "confidence": "EXTRACTED", "source_file": "backend/src/models/stock.py", "source_location": "L21", "weight": 1.0}, {"source": "stock_rationale_28", "target": "stock_companydetail", "relation": "rationale_for", "confidence": "EXTRACTED", "source_file": "backend/src/models/stock.py", "source_location": "L28", "weight": 1.0}, {"source": "stock_rationale_52", "target": "stock_topmover", "relation": "rationale_for", "confidence": "EXTRACTED", "source_file": "backend/src/models/stock.py", "source_location": "L52", "weight": 1.0}]}