{"nodes": [{"id": "translation", "label": "translation.py", "file_type": "code", "source_file": "backend/src/schemas/translation.py", "source_location": "L1"}, {"id": "translation_translationbase", "label": "TranslationBase", "file_type": "code", "source_file": "backend/src/schemas/translation.py", "source_location": "L10"}, {"id": "basemodel", "label": "BaseModel", "file_type": "code", "source_file": "", "source_location": ""}, {"id": "translation_translationcreate", "label": "TranslationCreate", "file_type": "code", "source_file": "backend/src/schemas/translation.py", "source_location": "L18"}, {"id": "translation_translationupdate", "label": "TranslationUpdate", "file_type": "code", "source_file": "backend/src/schemas/translation.py", "source_location": "L23"}, {"id": "translation_translationresponse", "label": "TranslationResponse", "file_type": "code", "source_file": "backend/src/schemas/translation.py", "source_location": "L30"}, {"id": "translation_config", "label": "Config", "file_type": "code", "source_file": "backend/src/schemas/translation.py", "source_location": "L38"}, {"id": "translation_translationpublicresponse", "label": "TranslationPublicResponse", "file_type": "code", "source_file": "backend/src/schemas/translation.py", "source_location": "L42"}, {"id": "translation_translationlistresponse", "label": "TranslationListResponse", "file_type": "code", "source_file": "backend/src/schemas/translation.py", "source_location": "L53"}, {"id": "translation_bulkimportitem", "label": "BulkImportItem", "file_type": "code", "source_file": "backend/src/schemas/translation.py", "source_location": "L61"}, {"id": "translation_bulkimportresponse", "label": "BulkImportResponse", "file_type": "code", "source_file": "backend/src/schemas/translation.py", "source_location": "L66"}, {"id": "translation_missingtranslation", "label": "MissingTranslation", "file_type": "code", "source_file": "backend/src/schemas/translation.py", "source_location": "L73"}, {"id": "translation_missingtranslationsresponse", "label": "MissingTranslationsResponse", "file_type": "code", "source_file": "backend/src/schemas/translation.py", "source_location": "L80"}, {"id": "translation_rationale_1", "label": "Pydantic schemas for stock translations.", "file_type": "rationale", "source_file": "backend/src/schemas/translation.py", "source_location": "L1"}, {"id": "translation_rationale_11", "label": "Base translation schema with common fields.", "file_type": "rationale", "source_file": "backend/src/schemas/translation.py", "source_location": "L11"}, {"id": "translation_rationale_19", "label": "Schema for creating a new translation.", "file_type": "rationale", "source_file": "backend/src/schemas/translation.py", "source_location": "L19"}, {"id": "translation_rationale_24", "label": "Schema for updating an existing translation.", "file_type": "rationale", "source_file": "backend/src/schemas/translation.py", "source_location": "L24"}, {"id": "translation_rationale_31", "label": "Schema for translation response.", "file_type": "rationale", "source_file": "backend/src/schemas/translation.py", "source_location": "L31"}, {"id": "translation_rationale_43", "label": "Schema for public translation lookup response.", "file_type": "rationale", "source_file": "backend/src/schemas/translation.py", "source_location": "L43"}, {"id": "translation_rationale_54", "label": "Schema for paginated translation list.", "file_type": "rationale", "source_file": "backend/src/schemas/translation.py", "source_location": "L54"}, {"id": "translation_rationale_62", "label": "Schema for a single item in bulk import.", "file_type": "rationale", "source_file": "backend/src/schemas/translation.py", "source_location": "L62"}, {"id": "translation_rationale_67", "label": "Schema for bulk import response.", "file_type": "rationale", "source_file": "backend/src/schemas/translation.py", "source_location": "L67"}, {"id": "translation_rationale_74", "label": "Schema for missing translation report.", "file_type": "rationale", "source_file": "backend/src/schemas/translation.py", "source_location": "L74"}, {"id": "translation_rationale_81", "label": "Schema for missing translations list.", "file_type": "rationale", "source_file": "backend/src/schemas/translation.py", "source_location": "L81"}], "edges": [{"source": "translation", "target": "datetime", "relation": "imports_from", "confidence": "EXTRACTED", "source_file": "backend/src/schemas/translation.py", "source_location": "L5", "weight": 1.0}, {"source": "translation", "target": "typing", "relation": "imports_from", "confidence": "EXTRACTED", "source_file": "backend/src/schemas/translation.py", "source_location": "L6", "weight": 1.0}, {"source": "translation", "target": "pydantic", "relation": "imports_from", "confidence": "EXTRACTED", "source_file": "backend/src/schemas/translation.py", "source_location": "L7", "weight": 1.0}, {"source": "translation", "target": "translation_translationbase", "relation": "contains", "confidence": "EXTRACTED", "source_file": "backend/src/schemas/translation.py", "source_location": "L10", "weight": 1.0}, {"source": "translation_translationbase", "target": "basemodel", "relation": "inherits", "confidence": "EXTRACTED", "source_file": "backend/src/schemas/translation.py", "source_location": "L10", "weight": 1.0}, {"source": "translation", "target": "translation_translationcreate", "relation": "contains", "confidence": "EXTRACTED", "source_file": "backend/src/schemas/translation.py", "source_location": "L18", "weight": 1.0}, {"source": "translation_translationcreate", "target": "translation_translationbase", "relation": "inherits", "confidence": "EXTRACTED", "source_file": "backend/src/schemas/translation.py", "source_location": "L18", "weight": 1.0}, {"source": "translation", "target": "translation_translationupdate", "relation": "contains", "confidence": "EXTRACTED", "source_file": "backend/src/schemas/translation.py", "source_location": "L23", "weight": 1.0}, {"source": "translation_translationupdate", "target": "basemodel", "relation": "inherits", "confidence": "EXTRACTED", "source_file": "backend/src/schemas/translation.py", "source_location": "L23", "weight": 1.0}, {"source": "translation", "target": "translation_translationresponse", "relation": "contains", "confidence": "EXTRACTED", "source_file": "backend/src/schemas/translation.py", "source_location": "L30", "weight": 1.0}, {"source": "translation_translationresponse", "target": "translation_translationbase", "relation": "inherits", "confidence": "EXTRACTED", "source_file": "backend/src/schemas/translation.py", "source_location": "L30", "weight": 1.0}, {"source": "translation", "target": "translation_config", "relation": "contains", "confidence": "EXTRACTED", "source_file": "backend/src/schemas/translation.py", "source_location": "L38", "weight": 1.0}, {"source": "translation", "target": "translation_translationpublicresponse", "relation": "contains", "confidence": "EXTRACTED", "source_file": "backend/src/schemas/translation.py", "source_location": "L42", "weight": 1.0}, {"source": "translation_translationpublicresponse", "target": "basemodel", "relation": "inherits", "confidence": "EXTRACTED", "source_file": "backend/src/schemas/translation.py", "source_location": "L42", "weight": 1.0}, {"source": "translation", "target": "translation_config", "relation": "contains", "confidence": "EXTRACTED", "source_file": "backend/src/schemas/translation.py", "source_location": "L49", "weight": 1.0}, {"source": "translation", "target": "translation_translationlistresponse", "relation": "contains", "confidence": "EXTRACTED", "source_file": "backend/src/schemas/translation.py", "source_location": "L53", "weight": 1.0}, {"source": "translation_translationlistresponse", "target": "basemodel", "relation": "inherits", "confidence": "EXTRACTED", "source_file": "backend/src/schemas/translation.py", "source_location": "L53", "weight": 1.0}, {"source": "translation", "target": "translation_bulkimportitem", "relation": "contains", "confidence": "EXTRACTED", "source_file": "backend/src/schemas/translation.py", "source_location": "L61", "weight": 1.0}, {"source": "translation_bulkimportitem", "target": "translation_translationbase", "relation": "inherits", "confidence": "EXTRACTED", "source_file": "backend/src/schemas/translation.py", "source_location": "L61", "weight": 1.0}, {"source": "translation", "target": "translation_bulkimportresponse", "relation": "contains", "confidence": "EXTRACTED", "source_file": "backend/src/schemas/translation.py", "source_location": "L66", "weight": 1.0}, {"source": "translation_bulkimportresponse", "target": "basemodel", "relation": "inherits", "confidence": "EXTRACTED", "source_file": "backend/src/schemas/translation.py", "source_location": "L66", "weight": 1.0}, {"source": "translation", "target": "translation_missingtranslation", "relation": "contains", "confidence": "EXTRACTED", "source_file": "backend/src/schemas/translation.py", "source_location": "L73", "weight": 1.0}, {"source": "translation_missingtranslation", "target": "basemodel", "relation": "inherits", "confidence": "EXTRACTED", "source_file": "backend/src/schemas/translation.py", "source_location": "L73", "weight": 1.0}, {"source": "translation", "target": "translation_missingtranslationsresponse", "relation": "contains", "confidence": "EXTRACTED", "source_file": "backend/src/schemas/translation.py", "source_location": "L80", "weight": 1.0}, {"source": "translation_missingtranslationsresponse", "target": "basemodel", "relation": "inherits", "confidence": "EXTRACTED", "source_file": "backend/src/schemas/translation.py", "source_location": "L80", "weight": 1.0}, {"source": "translation_rationale_1", "target": "translation", "relation": "rationale_for", "confidence": "EXTRACTED", "source_file": "backend/src/schemas/translation.py", "source_location": "L1", "weight": 1.0}, {"source": "translation_rationale_11", "target": "translation_translationbase", "relation": "rationale_for", "confidence": "EXTRACTED", "source_file": "backend/src/schemas/translation.py", "source_location": "L11", "weight": 1.0}, {"source": "translation_rationale_19", "target": "translation_translationcreate", "relation": "rationale_for", "confidence": "EXTRACTED", "source_file": "backend/src/schemas/translation.py", "source_location": "L19", "weight": 1.0}, {"source": "translation_rationale_24", "target": "translation_translationupdate", "relation": "rationale_for", "confidence": "EXTRACTED", "source_file": "backend/src/schemas/translation.py", "source_location": "L24", "weight": 1.0}, {"source": "translation_rationale_31", "target": "translation_translationresponse", "relation": "rationale_for", "confidence": "EXTRACTED", "source_file": "backend/src/schemas/translation.py", "source_location": "L31", "weight": 1.0}, {"source": "translation_rationale_43", "target": "translation_translationpublicresponse", "relation": "rationale_for", "confidence": "EXTRACTED", "source_file": "backend/src/schemas/translation.py", "source_location": "L43", "weight": 1.0}, {"source": "translation_rationale_54", "target": "translation_translationlistresponse", "relation": "rationale_for", "confidence": "EXTRACTED", "source_file": "backend/src/schemas/translation.py", "source_location": "L54", "weight": 1.0}, {"source": "translation_rationale_62", "target": "translation_bulkimportitem", "relation": "rationale_for", "confidence": "EXTRACTED", "source_file": "backend/src/schemas/translation.py", "source_location": "L62", "weight": 1.0}, {"source": "translation_rationale_67", "target": "translation_bulkimportresponse", "relation": "rationale_for", "confidence": "EXTRACTED", "source_file": "backend/src/schemas/translation.py", "source_location": "L67", "weight": 1.0}, {"source": "translation_rationale_74", "target": "translation_missingtranslation", "relation": "rationale_for", "confidence": "EXTRACTED", "source_file": "backend/src/schemas/translation.py", "source_location": "L74", "weight": 1.0}, {"source": "translation_rationale_81", "target": "translation_missingtranslationsresponse", "relation": "rationale_for", "confidence": "EXTRACTED", "source_file": "backend/src/schemas/translation.py", "source_location": "L81", "weight": 1.0}]}