{"nodes": [{"id": "admin_analytics", "label": "admin_analytics.py", "file_type": "code", "source_file": "backend/src/routers/admin_analytics.py", "source_location": "L1"}, {"id": "admin_analytics_get_analytics_overview", "label": "get_analytics_overview()", "file_type": "code", "source_file": "backend/src/routers/admin_analytics.py", "source_location": "L14"}, {"id": "admin_analytics_rationale_1", "label": "Admin Analytics API - Fetches analytics data from Cloudflare.", "file_type": "rationale", "source_file": "backend/src/routers/admin_analytics.py", "source_location": "L1"}, {"id": "admin_analytics_rationale_18", "label": "Get analytics overview - currently returns placeholder data.     Real analytics", "file_type": "rationale", "source_file": "backend/src/routers/admin_analytics.py", "source_location": "L18"}], "edges": [{"source": "admin_analytics", "target": "logging", "relation": "imports", "confidence": "EXTRACTED", "source_file": "backend/src/routers/admin_analytics.py", "source_location": "L4", "weight": 1.0}, {"source": "admin_analytics", "target": "fastapi", "relation": "imports_from", "confidence": "EXTRACTED", "source_file": "backend/src/routers/admin_analytics.py", "source_location": "L5", "weight": 1.0}, {"source": "admin_analytics", "target": "src_auth_admin_auth", "relation": "imports_from", "confidence": "EXTRACTED", "source_file": "backend/src/routers/admin_analytics.py", "source_location": "L7", "weight": 1.0}, {"source": "admin_analytics", "target": "admin_analytics_get_analytics_overview", "relation": "contains", "confidence": "EXTRACTED", "source_file": "backend/src/routers/admin_analytics.py", "source_location": "L14", "weight": 1.0}, {"source": "admin_analytics_rationale_1", "target": "admin_analytics", "relation": "rationale_for", "confidence": "EXTRACTED", "source_file": "backend/src/routers/admin_analytics.py", "source_location": "L1", "weight": 1.0}, {"source": "admin_analytics_rationale_18", "target": "admin_analytics_get_analytics_overview", "relation": "rationale_for", "confidence": "EXTRACTED", "source_file": "backend/src/routers/admin_analytics.py", "source_location": "L18", "weight": 1.0}]}