{"nodes": [{"id": "transformers", "label": "transformers.ts", "file_type": "code", "source_file": "frontend/src/services/api/transformers.ts", "source_location": "L1"}, {"id": "transformers_transformnodedata", "label": "transformNodeData()", "file_type": "code", "source_file": "frontend/src/services/api/transformers.ts", "source_location": "L89"}, {"id": "transformers_transformnode", "label": "transformNode()", "file_type": "code", "source_file": "frontend/src/services/api/transformers.ts", "source_location": "L105"}, {"id": "transformers_transformedge", "label": "transformEdge()", "file_type": "code", "source_file": "frontend/src/services/api/transformers.ts", "source_location": "L134"}, {"id": "transformers_transformgraphdata", "label": "transformGraphData()", "file_type": "code", "source_file": "frontend/src/services/api/transformers.ts", "source_location": "L149"}, {"id": "transformers_transformchartdatapoint", "label": "transformChartDataPoint()", "file_type": "code", "source_file": "frontend/src/services/api/transformers.ts", "source_location": "L166"}, {"id": "transformers_transformcompanydetail", "label": "transformCompanyDetail()", "file_type": "code", "source_file": "frontend/src/services/api/transformers.ts", "source_location": "L184"}, {"id": "transformers_transformstockevent", "label": "transformStockEvent()", "file_type": "code", "source_file": "frontend/src/services/api/transformers.ts", "source_location": "L208"}, {"id": "transformers_generatesparklinehistory", "label": "generateSparklineHistory()", "file_type": "code", "source_file": "frontend/src/services/api/transformers.ts", "source_location": "L229"}, {"id": "transformers_hydratenodewithstockdata", "label": "hydrateNodeWithStockData()", "file_type": "code", "source_file": "frontend/src/services/api/transformers.ts", "source_location": "L251"}, {"id": "transformers_transformapiepisodetomock", "label": "transformApiEpisodeToMock()", "file_type": "code", "source_file": "frontend/src/services/api/transformers.ts", "source_location": "L281"}], "edges": [{"source": "transformers", "target": "types", "relation": "imports_from", "confidence": "EXTRACTED", "source_file": "frontend/src/services/api/transformers.ts", "source_location": "L8", "weight": 1.0}, {"source": "transformers", "target": "mockdata", "relation": "imports_from", "confidence": "EXTRACTED", "source_file": "frontend/src/services/api/transformers.ts", "source_location": "L18", "weight": 1.0}, {"source": "transformers", "target": "index", "relation": "imports_from", "confidence": "EXTRACTED", "source_file": "frontend/src/services/api/transformers.ts", "source_location": "L19", "weight": 1.0}, {"source": "transformers", "target": "transformers_transformnodedata", "relation": "contains", "confidence": "EXTRACTED", "source_file": "frontend/src/services/api/transformers.ts", "source_location": "L89", "weight": 1.0}, {"source": "transformers", "target": "transformers_transformnode", "relation": "contains", "confidence": "EXTRACTED", "source_file": "frontend/src/services/api/transformers.ts", "source_location": "L105", "weight": 1.0}, {"source": "transformers", "target": "transformers_transformedge", "relation": "contains", "confidence": "EXTRACTED", "source_file": "frontend/src/services/api/transformers.ts", "source_location": "L134", "weight": 1.0}, {"source": "transformers", "target": "transformers_transformgraphdata", "relation": "contains", "confidence": "EXTRACTED", "source_file": "frontend/src/services/api/transformers.ts", "source_location": "L149", "weight": 1.0}, {"source": "transformers", "target": "transformers_transformchartdatapoint", "relation": "contains", "confidence": "EXTRACTED", "source_file": "frontend/src/services/api/transformers.ts", "source_location": "L166", "weight": 1.0}, {"source": "transformers", "target": "transformers_transformcompanydetail", "relation": "contains", "confidence": "EXTRACTED", "source_file": "frontend/src/services/api/transformers.ts", "source_location": "L184", "weight": 1.0}, {"source": "transformers", "target": "transformers_transformstockevent", "relation": "contains", "confidence": "EXTRACTED", "source_file": "frontend/src/services/api/transformers.ts", "source_location": "L208", "weight": 1.0}, {"source": "transformers", "target": "transformers_generatesparklinehistory", "relation": "contains", "confidence": "EXTRACTED", "source_file": "frontend/src/services/api/transformers.ts", "source_location": "L229", "weight": 1.0}, {"source": "transformers", "target": "transformers_hydratenodewithstockdata", "relation": "contains", "confidence": "EXTRACTED", "source_file": "frontend/src/services/api/transformers.ts", "source_location": "L251", "weight": 1.0}, {"source": "transformers", "target": "transformers_transformapiepisodetomock", "relation": "contains", "confidence": "EXTRACTED", "source_file": "frontend/src/services/api/transformers.ts", "source_location": "L281", "weight": 1.0}, {"source": "transformers_transformnode", "target": "transformers_transformnodedata", "relation": "calls", "confidence": "EXTRACTED", "source_file": "frontend/src/services/api/transformers.ts", "source_location": "L106", "weight": 1.0}, {"source": "transformers_hydratenodewithstockdata", "target": "transformers_generatesparklinehistory", "relation": "calls", "confidence": "EXTRACTED", "source_file": "frontend/src/services/api/transformers.ts", "source_location": "L255", "weight": 1.0}]}